dolbyio_rest_apis/__init__.py
dolbyio_rest_apis/core/__init__.py
dolbyio_rest_apis/core/helpers.py
dolbyio_rest_apis/core/http_context.py
dolbyio_rest_apis/core/http_request_error.py
dolbyio_rest_apis/core/rate_limiter.py
dolbyio_rest_apis/core/urls.py
dolbyio_rest_apis/media/__init__.py
dolbyio_rest_apis/media/analyze.py
dolbyio_rest_apis/media/analyze_music.py
dolbyio_rest_apis/media/analyze_speech.py
dolbyio_rest_apis/media/authentication.py
dolbyio_rest_apis/media/diagnose.py
dolbyio_rest_apis/media/enhance.py
dolbyio_rest_apis/media/io.py
dolbyio_rest_apis/media/jobs.py
dolbyio_rest_apis/media/mastering.py
dolbyio_rest_apis/media/transcode.py
dolbyio_rest_apis/media/webhooks.py
dolbyio_rest_apis/media/internal/__init__.py
dolbyio_rest_apis/media/internal/http_context.py
dolbyio_rest_apis/media/models/__init__.py
dolbyio_rest_apis/media/models/access_token.py
dolbyio_rest_apis/media/models/analyze_music_response.py
dolbyio_rest_apis/media/models/analyze_response.py
dolbyio_rest_apis/media/models/analyze_speech_response.py
dolbyio_rest_apis/media/models/diagnose_response.py
dolbyio_rest_apis/media/models/enhance_response.py
dolbyio_rest_apis/media/models/job_response.py
dolbyio_rest_apis/media/models/jobs_response.py
dolbyio_rest_apis/media/models/mastering_response.py
dolbyio_rest_apis/media/models/paged_response.py
dolbyio_rest_apis/media/models/result_error.py
dolbyio_rest_apis/media/models/transcode_response.py
dolbyio_rest_apis/media/models/webhook.py
dolbyio_rest_apis/streaming/__init__.py
dolbyio_rest_apis/streaming/account.py
dolbyio_rest_apis/streaming/cluster.py
dolbyio_rest_apis/streaming/publish_token.py
dolbyio_rest_apis/streaming/stream.py
dolbyio_rest_apis/streaming/subscribe_token.py
dolbyio_rest_apis/streaming/webhooks.py
dolbyio_rest_apis/streaming/internal/__init__.py
dolbyio_rest_apis/streaming/internal/http_context.py
dolbyio_rest_apis/streaming/models/__init__.py
dolbyio_rest_apis/streaming/models/account.py
dolbyio_rest_apis-5.0.0.dist-info/LICENSE
dolbyio_rest_apis-5.0.0.dist-info/METADATA
dolbyio_rest_apis-5.0.0.dist-info/WHEEL
dolbyio_rest_apis-5.0.0.dist-info/top_level.txt
dolbyio_rest_apis-5.0.0.dist-info/RECORD
