Metadata-Version: 2.1
Name: dolbyio-rest-apis
Version: 5.0.0
Summary: A Python wrapper for the Dolby.io REST APIs.
Home-page: https://github.com/dolbyio/dolbyio-rest-apis-client-python
Author: Dolby.io
Author-email: fabien.lavocat@dolby.com
License: MIT
Project-URL: Documentation, https://docs.dolby.io/streaming-apis/reference
Project-URL: Source, https://github.com/dolbyio/dolbyio-rest-apis-client-python
Project-URL: Bug Tracker, https://github.com/dolbyio/dolbyio-rest-apis-client-python/issues
Platform: UNKNOWN
Classifier: License :: OSI Approved :: MIT License
Classifier: Programming Language :: Python
Classifier: Programming Language :: Python :: 3
Classifier: Programming Language :: Python :: 3.10
Classifier: Programming Language :: Python :: 3.11
Classifier: Programming Language :: Python :: 3 :: Only
Classifier: Operating System :: OS Independent
Classifier: Intended Audience :: Developers
Requires-Python: >=3.10
License-File: LICENSE
Requires-Dist: aiofiles (>=0.7.0)
Requires-Dist: aiohttp-retry (>=2.4.6)
Requires-Dist: aiohttp (>=3.7.4)
Requires-Dist: certifi (>=2024.7.4)
Requires-Dist: dataclasses-json (>=0.6.7)
